colouration/Colour.py
colouration/Gradient.py
colouration/Scheme.py
colouration/__init__.py
colouration/colour_schemes.py
colouration/colourize.py
colouration/convert_rgb_to_hsl.py
colouration/data_files/colour_schemes.pickle
colouration/data_files/svg_colours.pickle
colouration/data_files/x11_colours.pickle
colouration-2020.7.26.dist-info/LICENSE
colouration-2020.7.26.dist-info/METADATA
colouration-2020.7.26.dist-info/WHEEL
colouration-2020.7.26.dist-info/top_level.txt
colouration-2020.7.26.dist-info/zip-safe
colouration-2020.7.26.dist-info/RECORD
