Metadata-Version: 2.1
Name: colouration
Version: 2020.7.26
Summary: Python library for working with colours
Home-page: https://github.com/idin/colouration
Author: Idin
Author-email: py@idin.ca
License: MIT
Keywords: colour
Platform: UNKNOWN
Classifier: Development Status :: 3 - Alpha
Classifier: Intended Audience :: Developers
Classifier: License :: OSI Approved :: MIT License
Classifier: Programming Language :: Python :: 3 :: Only
Classifier: Programming Language :: Python :: 3.6
Classifier: Programming Language :: Python :: 3.7
Classifier: Topic :: Software Development :: Libraries :: Python Modules
Requires-Python: ~=3.6
